plakativ.py
plakativ-0.5.1.data/data/share/applications/de.mister-muffin.plakativ.desktop
plakativ-0.5.1.data/data/share/metainfo/plakativ.appdata.xml
plakativ-0.5.1.data/data/share/pixmaps/plakativ.svg
plakativ-0.5.1.dist-info/LICENSE
plakativ-0.5.1.dist-info/METADATA
plakativ-0.5.1.dist-info/WHEEL
plakativ-0.5.1.dist-info/entry_points.txt
plakativ-0.5.1.dist-info/top_level.txt
plakativ-0.5.1.dist-info/zip-safe
plakativ-0.5.1.dist-info/RECORD
