Metadata-Version: 2.1
Name: plakativ
Version: 0.5.1
Summary: Convert a PDF into a large poster that can be printed on multiple smaller pages.
Home-page: https://gitlab.mister-muffin.de/josch/plakativ
Download-URL: https://gitlab.mister-muffin.de/josch/plakativ/repository/archive.tar.gz?ref=0.5.1
Author: Johannes Schauer Marin Rodrigues
Author-email: josch@mister-muffin.de
License: GPL-3
Keywords: pdf poster
Classifier: Development Status :: 5 - Production/Stable
Classifier: Intended Audience :: Developers
Classifier: Intended Audience :: Other Audience
Classifier: Environment :: Console
Classifier: Environment :: MacOS X
Classifier: Environment :: Win32 (MS Windows)
Classifier: Environment :: X11 Applications
Classifier: Programming Language :: Python
Classifier: Programming Language :: Python :: 3
Classifier: Programming Language :: Python :: 3.7
Classifier: Programming Language :: Python :: Implementation :: CPython
Classifier: Programming Language :: Python :: Implementation :: PyPy
Classifier: License :: OSI Approved :: GNU General Public License v3 (GPLv3)
Classifier: Natural Language :: English
Classifier: Operating System :: OS Independent
License-File: LICENSE
Requires-Dist: PyMuPDF
Requires-Dist: img2pdf
